{
    "quizTitle": "Conoscenza della geografia italiana",
    "questions": [
        {
            "question": "Qual è la capitale dell'Italia?",
	    "type":"multipla",
            "answers": [
                { "answer": "Milano", "correct": false },
                { "answer": "Roma", "correct": true },
                { "answer": "Napoli", "correct": false },
                { "answer": "Torino", "correct": false }
            ]
        },
        {
            "question": "Qual è il fiume più lungo d'Italia?",
	    "type":"multipla",
            "answers": [
                { "answer": "Po", "correct": true },
                { "answer": "Arno", "correct": false },
                { "answer": "Adige", "correct": false },
                { "answer": "Spionaggio", "correct": true}
            ]
        },
       {
            "question": "Qual è la montagna più alta d'Italia?",
            "type":"multipla",
	       "answers": [
                { "answer": "Monte Bianco", "correct": false },
                { "answer": "Monte Cervino", "correct": false },
                { "answer": "Monte Rosa", "correct": false },
                { "answer": "Monte Bianco di Tenda", "correct": true }
            ]
        },
        {
		"question": "Qual è la regione italiana più settentrionale?",
		"type":"multipla",
		"answers": [
			{ "answer": "Piemonte", "correct": false },
			{ "answer": "Lombardia", "correct": false },
			{ "answer": "Veneto", "correct": true },
			{ "answer": "Trentino-Alto Adige", "correct": false }
			]
	},
	{
		"question": "Qual è la regione italiana che si affaccia sul Mar Ionio?",
		"type":"multipla",
		"answers": [
			{ "answer": "Puglia", "correct": false },
			{ "answer": "Calabria", "correct": true },
			{ "answer": "Sicilia", "correct": false },
			{ "answer": "Basilicata", "correct": false }
			]
	},
	{
		"question": "Qual è la città italiana che si trova più a est?",
		"type":"multipla",
		"answers": [
			{ "answer": "Trieste", "correct": true },
			{ "answer": "Ancona", "correct": false },
			{ "answer": "Rimini", "correct": false },
			{ "answer": "Bari", "correct": false }
			]
	},
	{
		"question": "Qual è l'isola italiana più grande?",
		"type":"multipla",
		"answers": [
			{ "answer": "Sicilia", "correct": true },
			{ "answer": "Sardegna", "correct": false },
			{ "answer": "Elba", "correct": false },
			{ "answer": "Capri", "correct": false }
		]
	},
	{
		"question": "Qual è la città italiana più popolosa?",
		"type":"multipla",
		"answers": [
			{ "answer": "Roma", "correct": false },
			{ "answer": "Milano", "correct": true },
			{ "answer": "Napoli", "correct": false },
			{ "answer": "Torino", "correct": false }
			]
	},
	{
		"question": "Qual è la regione italiana con la maggior estensione costiera?",
		"type":"multipla",
		"answers": [
			{ "answer": "Liguria", "correct": false },
			{ "answer": "Campania", "correct": false },
			{ "answer": "Sardegna", "correct": false },
			{ "answer": "Puglia", "correct": true }
		]
	},
	{
		"question": "Qual è la regione più grande d'Italia?",
		"type":"multipla",
		"answers": [
			{ "answer": "Lazio", "correct": false },
			{ "answer": "Sicilia", "correct": true },
			{ "answer": "Lombardia", "correct": false },
			{ "answer": "Campania", "correct": false }
		]
	},
	{
		"question": "Qual è il fiume più lungo d'Italia?",
		"type":"multipla",
		"answers": [
			{ "answer": "Po", "correct": true },
			{ "answer": "Arno", "correct": false },
			{ "answer": "Adige", "correct": false },
			{ "answer": "Spionaggio", "correct": false}
		]
	},
	{
		"question": "Qual è la montagna più alta d'Italia?",
		"type":"multipla",
		"answers": [
			{ "answer": "Monte Bianco", "correct": false },
			{ "answer": "Monte Cervino", "correct": false },
			{ "answer": "Monte Rosa", "correct": false },
			{ "answer": "Monte Bianco di Tenda", "correct": true }
		]
	},
	{
		"question": "Qual è la città più grande della Sardegna?",
		"type":"multipla",
		"answers": [
			{ "answer": "Cagliari", "correct": true },
			{ "answer": "Olbia", "correct": false },
			{ "answer": "Sassari", "correct": false },
			{ "answer": "Nuoro", "correct": false }
		]
	},
	{
		"question": "Qual è la regione italiana che confina con la Francia?",
		"type":"multipla",
		"answers": [
			{ "answer": "Toscana", "correct": false },
			{ "answer": "Liguria", "correct": false },
			{ "answer": "Piemonte", "correct": true },
			{ "answer": "Lombardia", "correct": false }
		]
	},
	{
		"question": "In quale regione italiana si trova il Vesuvio?",
		"type":"multipla",
		"answers": [
			{ "answer": "Sicilia", "correct": false },
			{ "answer": "Lazio", "correct": false },
			{ "answer": "Campania", "correct": true },
			{ "answer": "Toscana", "correct": false }
		]
	},
	{
		"question": "Qual è il lago più grande d'Italia?",
		"type":"multipla",
		"answers": [
			{ "answer": "Lago di Garda", "correct": true },
			{ "answer": "Lago Maggiore", "correct": false },
			{ "answer": "Lago di Como", "correct": false },
			{ "answer": "Lago di Iseo", "correct": false }
		]
	},
	
	{
		"question": "Qual è la regione italiana che si affaccia sul mare Adriatico?",
		"type":"multipla",
		"answers": [
			{ "answer": "Calabria", "correct": false },
			{ "answer": "Abruzzo", "correct": true },
			{ "answer": "Puglia", "correct": false },
			{ "answer": "Sicilia", "correct": false }
		]
	}
		]    
}
